apps/excute/a.py
apps/excute/views.py
apps/heartbeat/views.py
common/context.py
common/decorator.py
common/dependencies.py
common/logger.py
common/models.py
common/pagination.py
common/response.py
common/schemas.py
common/service.py
common/status.py
config/__init__.py
config/base.py
config/dev.py
config/prod.py
core/database.py
core/exception_handler.py
core/router.py
events/initialize.py
nacos/pynacos.py
utils/__init__.py
utils/dynamic_import.py
misds-0.1.0.dist-info/METADATA
misds-0.1.0.dist-info/WHEEL
misds-0.1.0.dist-info/top_level.txt
misds-0.1.0.dist-info/RECORD
